eai_camp/init.py
eai_camp-0.0.1.dist-info/METADATA
eai_camp-0.0.1.dist-info/WHEEL
eai_camp-0.0.1.dist-info/entry_points.txt
eai_camp-0.0.1.dist-info/top_level.txt
eai_camp-0.0.1.dist-info/RECORD
