Metadata-Version: 2.4
Name: eai-camp
Version: 0.0.1
Summary: Enterprise AI Agent Compliance & Audit Management Platform
Home-page: https://github.com/yourusername/eai-camp
Author: EAI-CAMP Development Team
Author-email: EAI-CAMP Development Team <support@eai-camp.com>
License: MIT
Project-URL: Homepage, https://github.com/yourusername/eai-camp
Project-URL: Repository, https://github.com/yourusername/eai-camp
Project-URL: Documentation, https://eai-camp.readthedocs.io/
Project-URL: Issues, https://github.com/yourusername/eai-camp/issues
Keywords: ai,compliance,audit,enterprise,agents,governance
Classifier: Development Status :: 3 - Alpha
Classifier: Intended Audience :: Developers
Classifier: License :: OSI Approved :: MIT License
Classifier: Programming Language :: Python :: 3
Classifier: Programming Language :: Python :: 3.8
Classifier: Programming Language :: Python :: 3.9
Classifier: Programming Language :: Python :: 3.10
Classifier: Programming Language :: Python :: 3.11
Requires-Python: >=3.8
Requires-Dist: streamlit>=1.28.0
Requires-Dist: pandas>=1.5.0
Requires-Dist: numpy>=1.21.0
Requires-Dist: plotly>=5.0.0
Requires-Dist: pyjwt>=2.8.0
Requires-Dist: bcrypt>=4.0.0
Requires-Dist: sqlalchemy>=2.0.0
Requires-Dist: asyncio-mqtt>=0.13.0
Requires-Dist: pydantic>=2.0.0
Requires-Dist: python-dotenv>=1.0.0
Requires-Dist: requests>=2.28.0
Requires-Dist: aiohttp>=3.8.0
Requires-Dist: cryptography>=41.0.0
Provides-Extra: dev
Requires-Dist: pytest>=7.0.0; extra == "dev"
Requires-Dist: pytest-asyncio>=0.21.0; extra == "dev"
Requires-Dist: pytest-cov>=4.0.0; extra == "dev"
Requires-Dist: black>=22.0.0; extra == "dev"
Requires-Dist: flake8>=5.0.0; extra == "dev"
Requires-Dist: mypy>=1.0.0; extra == "dev"
Requires-Dist: pre-commit>=2.20.0; extra == "dev"
Provides-Extra: docs
Requires-Dist: sphinx>=5.0.0; extra == "docs"
Requires-Dist: sphinx-rtd-theme>=1.0.0; extra == "docs"
Requires-Dist: myst-parser>=0.18.0; extra == "docs"
Dynamic: author
Dynamic: home-page
Dynamic: requires-python
